tubeline/TubeLine.py
tubeline/__init__.py
tubeline/analyzer.py
tubeline/config.py
tubeline/downloader.py
tubeline/stt.py
tubeline-0.1.0.dist-info/METADATA
tubeline-0.1.0.dist-info/WHEEL
tubeline-0.1.0.dist-info/top_level.txt
tubeline-0.1.0.dist-info/RECORD
