Metadata-Version: 2.4
Name: TubeLine
Version: 0.1.0
Summary: YouTube Timeline Pipeline
Author: 강은성
Author-email: grootseong@gmail.com
Keywords: youtube,speech-to-text,deepgram,gemini,ai,stt,video-analysis,timeline,time,line
Classifier: Programming Language :: Python :: 3
Classifier: Programming Language :: Python :: 3.10
Classifier: Programming Language :: Python :: 3.11
Classifier: Programming Language :: Python :: 3.12
Classifier: License :: OSI Approved :: MIT License
Classifier: Operating System :: OS Independent
Classifier: Topic :: Multimedia :: Sound/Audio :: Speech
Classifier: Topic :: Multimedia :: Video
Classifier: Topic :: Scientific/Engineering :: Artificial Intelligence
Requires-Python: >=3.10
Requires-Dist: requests>=2.31.0
Requires-Dist: google-genai>=0.3.0
Requires-Dist: yt-dlp>=2024.4.9
Dynamic: author
Dynamic: author-email
Dynamic: classifier
Dynamic: description
Dynamic: description-content-type
Dynamic: keywords
Dynamic: requires-dist
Dynamic: requires-python
Dynamic: summary
